llama_index/embeddings/dashscope/__init__.py
llama_index/embeddings/dashscope/base.py
llama_index_embeddings_dashscope-0.4.1.dist-info/METADATA
llama_index_embeddings_dashscope-0.4.1.dist-info/WHEEL
llama_index_embeddings_dashscope-0.4.1.dist-info/licenses/LICENSE
llama_index_embeddings_dashscope-0.4.1.dist-info/RECORD
