Metadata-Version: 2.4
Name: llama-index-embeddings-dashscope
Version: 0.4.1
Summary: llama-index embeddings dashscope integration
Author: liuyhwangyh
License-Expression: MIT
License-File: LICENSE
Requires-Python: <4.0,>=3.9
Requires-Dist: dashscope>1.10.0
Requires-Dist: llama-index-core<0.15,>=0.13.0
